aind_settings_utils/__init__.py
aind_settings_utils/aws.py
aind_settings_utils-0.1.0.dist-info/licenses/LICENSE
aind_settings_utils-0.1.0.dist-info/METADATA
aind_settings_utils-0.1.0.dist-info/WHEEL
aind_settings_utils-0.1.0.dist-info/top_level.txt
aind_settings_utils-0.1.0.dist-info/RECORD
