Metadata-Version: 2.4
Name: aind-settings-utils
Version: 0.1.0
Summary: Utility package to add custom pydantic settings sources
Author: Allen Institute for Neural Dynamics
License: MIT
Classifier: Programming Language :: Python :: 3
Requires-Python: >=3.9
License-File: LICENSE
Requires-Dist: pydantic-settings[aws-secrets-manager]>=2.9.0
Requires-Dist: pydantic>=2.0
Provides-Extra: dev
Requires-Dist: black; extra == "dev"
Requires-Dist: coverage; extra == "dev"
Requires-Dist: flake8; extra == "dev"
Requires-Dist: interrogate; extra == "dev"
Requires-Dist: isort; extra == "dev"
Requires-Dist: Sphinx; extra == "dev"
Requires-Dist: furo; extra == "dev"
Dynamic: license-file
